Metadata-Version: 2.1
Name: abork-path-analyser
Version: 1.0.0
Summary: Path Analyser
Home-page: UNKNOWN
Author: Alex Bork
License: UNKNOWN
Platform: UNKNOWN
